{
   "engageExperienceApp": {
      "testExecDir": "./testResources/testExecutionFiles/engageExperienceApp/",
      "environments": {
         "qa": {
            "url": "https://qa.engage.comprodls.com",
            "reportDirRepo": "https://d29cns2xkhqbb2.cloudfront.net"
         },
         "production": {
            "url": "https://sm.engage.comprodls.com/",
            "reportDirRepo": "https://d29cns2xkhqbb2.cloudfront.net/engage/production/"
         }
      }
   },
   "difusionExperienceApp": {
      "testExecDir": "./testResources/testExecutionFiles/difusionExperienceApp/",
      "environments": {
         "qa": {
            "url": "https://engage-difusion-dev1.comprodls.com",
            "reportDirRepo": "https://d29cns2xkhqbb2.cloudfront.net"
         },
         "production": {
            "url": "https://engage-dev2.comprodls.com",
            "reportDirRepo": "https://d29cns2xkhqbb2.cloudfront.net"
         }
      }
   },
   "backoffice": {
      "testExecDir": "./testResources/testExecutionFiles/backoffice/",
      "environments": {
         "qa": {
            "url": "https://backoffice-difusion-dev1.comprodls.com/",
            "reportDirRepo": "https://d29cns2xkhqbb2.cloudfront.net"
         },
         "production": {
            "url": "https://backoffice-difusion-dev2.comprodls.com/",
            "reportDirRepo": "https://d29cns2xkhqbb2.cloudfront.net"
         }
      }
   },
   "assessmentEditor": {
      "testExecDir": "./testResources/testExecutionFiles/assessmentEditor/",
      "environments": {
         "qa": {
            "url": "https://backoffice-difusion-dev1.comprodls.com"
         }
      }
   },
   "itemPlayerTestbench": {
      "testExecDir": "./testdata/testExecutionFiles/itemPlayerTestbench/",
      "environments": {
         "testbench": {
            "url": "https://dev.engage.comprodls.com/",
            "username": "compro",
            "password": "c0mpr0"
         }
      }
   }
}