{
  "quizName": {
    "type": "Native Engage Learning Object",
    "name": "Kids MCQ Quiz",
    "question": [
      {
        "number": 1,
        "quesType": "kids-mcqsr-item-player",
        "quesTitle": "Look at the following figure and count number",
        "instructionText": null,
        "promptText": null,
        "viewLabels": {
          "instructionHeading": null,
          "selectOneLabel": "Select one",
          "selectOneOrMoreLabel": null,
          "selectFromDropdownLabel": null,
          "matchingLeftLabel": null,
          "matchingRightLabel": null,
          "zoomLabel": null,
          "selectLabel": null,
          "noneLabel": null,
          "clearLabel": null
        },
        "mediaType": "image",
        "subQues": [
          [
            "1",
            "How many rectangles are there ?",
            null
          ],
          [
            "2",
            "How many triangles are there ?",
            null
          ],
          [
            "3",
            "How many squares are there ?",
            null
          ]
        ],
        "answerKey": [
          [
            "1-O1",
            "2",
            null,
            null,
            null
          ],
          [
            "1-O2",
            "1",
            "select",
            "correct",
            null
          ],
          [
            "1-O3",
            "3",
            null,
            null,
            null
          ],
          [
            "2-O1",
            "2",
            "select",
            "correct",
            null
          ],
          [
            "2-O2",
            "1",
            null,
            null,
            null
          ],
          [
            "2-O3",
            "5",
            null,
            null,
            null
          ],
          [
            "3-O1",
            "2",
            null,
            null,
            null
          ],
          [
            "3-O2",
            "3",
            "select",
            "correct",
            null
          ],
          [
            "3-O3",
            "5",
            null,
            null,
            null
          ]
        ],
        "scenario1": [],
        "scenario2": []
      }
    ]
  }
}